bricksdk/__init__.py
bricksdk/base_brick.py
bricksdk/brick_commands/brick
bricksdk/brick_commands/command_handler.py
bricksdk/brick_commands/create.py
bricksdk/brick_commands/proto.py
bricksdk/brick_commands/templates/generic/brick/__init__.py
bricksdk/brick_commands/templates/generic/brick/processor.py
bricksdk/brick_commands/templates/generic/configurations/debug.json
bricksdk/brick_commands/templates/generic/main.py
bricksdk/brick_commands/templates/generic/meta.json
bricksdk/brick_commands/templates/generic/protos/image_classification_1.proto
bricksdk/brick_commands/templates/input/brick/__init__.py
bricksdk/brick_commands/templates/input/brick/processor.py
bricksdk/brick_commands/templates/input/configurations/debug.json
bricksdk/brick_commands/templates/input/main.py
bricksdk/brick_commands/templates/input/meta.json
bricksdk/brick_commands/templates/input/protos/image_classification_1.proto
bricksdk/brick_processors/__init__.py
bricksdk/brick_processors/base_brick_processor.py
bricksdk/brick_processors/generic_brick_processor.py
bricksdk/brick_processors/input_brick_processor.py
bricksdk/configurations/__init__.py
bricksdk/configurations/configuration.py
bricksdk/configurations/configuration_detector/__init__.py
bricksdk/configurations/configuration_loader/__init__.py
bricksdk/configurations/configuration_validator/__init__.py
bricksdk/connectors/__init__.py
bricksdk/connectors/base_connector.py
bricksdk/connectors/connector_types.py
bricksdk/connectors/grpc/__init__.py
bricksdk/connectors/grpc/grpc_connector.py
bricksdk/connectors/grpc/grpc_input_connector.py
bricksdk/connectors/grpc/grpc_output_connector.py
bricksdk/connectors/grpc/proto_processor/__init__.py
bricksdk/connectors/grpc/proto_processor/processor.py
bricksdk/observer/__init__.py
bricksdk/observer/events.py
bricksdk/observer/publisher.py
bricksdk/proto_store/__init__.py
bricksdk/proto_store/base_proto_store.py
bricksdk/proto_store/protos/detection_image_caster_5.proto
bricksdk-0.1.21.dist-info/WHEEL
bricksdk-0.1.21.dist-info/METADATA
bricksdk-0.1.21.dist-info/RECORD
